folprover_mcp/__init__.py
folprover_mcp/fol_parser.py
folprover_mcp/provers.py
folprover_mcp/server.py
folprover_mcp/simple_prover.py
folprover_mcp/tptp_converter.py
folprover_mcp-0.1.0.dist-info/METADATA
folprover_mcp-0.1.0.dist-info/WHEEL
folprover_mcp-0.1.0.dist-info/entry_points.txt
folprover_mcp-0.1.0.dist-info/licenses/LICENSE
folprover_mcp-0.1.0.dist-info/RECORD
