Metadata-Version: 2.4
Name: folprover-mcp
Version: 0.1.0
Summary: MCP server for First-Order Logic provers (Vampire, E)
Project-URL: Homepage, https://github.com/NewJerseyStyle/folprover-mcp
Project-URL: Repository, https://github.com/NewJerseyStyle/folprover-mcp
Author: David Xu
License-Expression: MIT
License-File: LICENSE
Keywords: eprover,first-order-logic,fol,mcp,theorem-proving,vampire
Classifier: Development Status :: 4 - Beta
Classifier: Intended Audience :: Developers
Classifier: License :: OSI Approved :: MIT License
Classifier: Programming Language :: Python :: 3
Classifier: Programming Language :: Python :: 3.10
Classifier: Programming Language :: Python :: 3.11
Classifier: Programming Language :: Python :: 3.12
Requires-Python: >=3.10
Requires-Dist: mcp>=1.0.0
Requires-Dist: nltk>=3.8.0
Requires-Dist: ply>=3.11
Provides-Extra: dev
Requires-Dist: pytest-asyncio>=0.21.0; extra == 'dev'
Requires-Dist: pytest>=7.0.0; extra == 'dev'
